setup.py
django_config.egg-info/PKG-INFO
django_config.egg-info/SOURCES.txt
django_config.egg-info/dependency_links.txt
django_config.egg-info/top_level.txt
djangoconfig/__init__.py
djangoconfig/deployment.py